lombardi/__init__.py
lombardi/cli.py
lombardi/analyzers/__init__.py
lombardi/analyzers/antipattern_detector.py
lombardi/analyzers/complexity_analyzer.py
lombardi/analyzers/optimization_suggester.py
lombardi/integrations/__init__.py
lombardi/integrations/sqlmesh_audit.py
lombardi/rules/__init__.py
lombardi/rules/bigquery_rules.py
lombardi/rules/snowflake_rules.py
lombardi-0.1.6.dist-info/METADATA
lombardi-0.1.6.dist-info/WHEEL
lombardi-0.1.6.dist-info/entry_points.txt
lombardi-0.1.6.dist-info/RECORD
