Metadata-Version: 2.4
Name: lombardi
Version: 0.1.6
Summary: SQL performance analysis and optimization advisor with SQLMesh integration
Project-URL: Homepage, https://github.com/Doctacon/lombardi
Project-URL: Repository, https://github.com/Doctacon/lombardi
Project-URL: Issues, https://github.com/Doctacon/lombardi/issues
Author-email: Connor Lough <loughondata@protonmail.com>
License: MIT
Keywords: data,optimization,performance,sql,sqlmesh
Classifier: Development Status :: 3 - Alpha
Classifier: Intended Audience :: Developers
Classifier: License :: OSI Approved :: MIT License
Classifier: Programming Language :: Python :: 3
Classifier: Programming Language :: Python :: 3.11
Classifier: Programming Language :: Python :: 3.12
Classifier: Topic :: Database
Classifier: Topic :: Software Development :: Quality Assurance
Requires-Python: >=3.11
Requires-Dist: pydantic>=2.0.0
Requires-Dist: rich>=13.0.0
Requires-Dist: sqlglot>=25.0.0
Requires-Dist: sqlmesh>=0.100.0
Requires-Dist: typer>=0.12.0
Provides-Extra: dev
Requires-Dist: pytest-cov>=4.0.0; extra == 'dev'
Requires-Dist: pytest>=7.0.0; extra == 'dev'
Requires-Dist: ruff>=0.1.0; extra == 'dev'
